{
  "id": "ikimon-ntc-led-kinoko",
  "manufacturer_id": "ikimon",
  "manufacturer_name": "いきもん",
  "brand_name": null,
  "series_name": null,
  "product_name": "LEDきのこライトコレクション",
  "release_year": null,
  "release_month": null,
  "release_week": null,
  "release_date": null,
  "preview_image_url": "https://naturetechnicolour.com/wp-content/uploads/2020/01/stc_led_mushroom_light_dp_a.jpg",
  "preview_image_source_url": "https://naturetechnicolour.com/ntc_led_kinoko/",
  "price_yen": null,
  "variant_count": null,
  "jan_code": null,
  "official_url": "https://naturetechnicolour.com/ntc_led_kinoko/",
  "source_url": "https://naturetechnicolour.com/ntc_led_kinoko/",
  "first_detected_at": "2026-05-13T19:05:49+09:00",
  "last_checked_at": "2026-05-13T19:05:49+09:00",
  "product_path": "products/ikimon-ntc-led-kinoko.json",
  "copyright_notice": "© 2015 IKIMON",
  "data_policy": {
    "source_verified": true,
    "uses_official_image": false,
    "uses_official_description": false
  }
}
