{
  "id": "ip4-2022-07-rascal-tbox",
  "manufacturer_id": "ip4",
  "manufacturer_name": "アイピーフォー",
  "brand_name": "あらいぐまラスカル",
  "series_name": null,
  "product_name": "クラシックデザインBOXティッシュカバー",
  "release_year": null,
  "release_month": null,
  "release_week": null,
  "release_date": null,
  "preview_image_url": "https://www.ip4.co.jp/ip4_index/wp-content/uploads/2022/06/VD2562_1000px-800x800.jpg",
  "preview_image_source_url": "https://www.ip4.co.jp/cupsuletoy/2022_07__rascal_tbox/",
  "price_yen": 400,
  "variant_count": 6,
  "jan_code": null,
  "official_url": "https://www.ip4.co.jp/cupsuletoy/2022_07__rascal_tbox/",
  "source_url": "https://www.ip4.co.jp/cupsuletoy/2022_07__rascal_tbox/",
  "first_detected_at": "2026-05-14T16:10:42+09:00",
  "last_checked_at": "2026-05-14T16:10:42+09:00",
  "product_path": "products/ip4-2022-07-rascal-tbox.json",
  "copyright_notice": "©NIPPON ANIMATION CO.,LTD.",
  "data_policy": {
    "source_verified": true,
    "uses_official_image": false,
    "uses_official_description": false
  }
}
