{
  "id": "kitanclub-seiza",
  "manufacturer_id": "kitanclub",
  "manufacturer_name": "キタンクラブ",
  "brand_name": null,
  "series_name": null,
  "product_name": "シリーズ生きる ─ 第五夜 ─ 正座",
  "release_year": 2013,
  "release_month": 8,
  "release_week": null,
  "release_date": null,
  "preview_image_url": "https://kitan.jp/wp-content/uploads/2013/09/seiza_DP_Re.jpg",
  "preview_image_source_url": "https://kitan.jp/products/seiza/",
  "price_yen": 300,
  "variant_count": 7,
  "jan_code": null,
  "official_url": "https://kitan.jp/products/seiza/",
  "source_url": "https://kitan.jp/products/seiza/",
  "first_detected_at": "2026-05-14T09:13:25+09:00",
  "last_checked_at": "2026-05-14T09:13:25+09:00",
  "product_path": "products/kitanclub-seiza.json",
  "copyright_notice": "©Toshio Asakura",
  "data_policy": {
    "source_verified": true,
    "uses_official_image": false,
    "uses_official_description": false
  }
}
