{
  "id": "qualia-ouen-sp",
  "manufacturer_id": "qualia",
  "manufacturer_name": "Qualia",
  "brand_name": null,
  "series_name": null,
  "product_name": "お仕事を頑張っている人の応援スクエアポーチ",
  "release_year": 2026,
  "release_month": 3,
  "release_week": null,
  "release_date": null,
  "preview_image_url": "https://qualia-45.jp/wp-content/uploads/oshigoto_pouch_DP_OL.jpg",
  "preview_image_source_url": "https://qualia-45.jp/distinations/ouen_sp/",
  "price_yen": 400,
  "variant_count": 6,
  "jan_code": null,
  "official_url": "https://qualia-45.jp/distinations/ouen_sp/",
  "source_url": "https://qualia-45.jp/distinations/ouen_sp/",
  "first_detected_at": "2026-05-13T16:15:44+09:00",
  "last_checked_at": "2026-05-16T18:00:29+09:00",
  "product_path": "products/qualia-ouen-sp.json",
  "copyright_notice": "©おだ犬",
  "data_policy": {
    "source_verified": true,
    "uses_official_image": false,
    "uses_official_description": false
  }
}
