{
  "schema_version": "1.0.0",
  "generated_at": "2026-05-17T09:22:06+09:00",
  "year": 2021,
  "month": 11,
  "items": [
    {
      "id": "bandai-gashapon-4549660760474000",
      "manufacturer_id": "bandai-gashapon",
      "manufacturer_name": "バンダイ ガシャポン",
      "brand_name": null,
      "series_name": null,
      "product_name": "最強ジャンプ２０２１年１２月号 かまきり02",
      "release_year": 2021,
      "release_month": 11,
      "release_week": 1,
      "release_date": null,
      "preview_image_url": "https://bandai-a.akamaihd.net/bc/img/model/xl/1000166351_1.jpg",
      "preview_image_source_url": "https://gashapon.jp/products/detail.php?jan_code=4549660760474000",
      "price_yen": 300,
      "variant_count": 6,
      "jan_code": null,
      "official_url": "https://gashapon.jp/products/detail.php?jan_code=4549660760474000",
      "source_url": "https://gashapon.jp/products/detail.php?jan_code=4549660760474000",
      "first_detected_at": "2026-05-14T16:14:39+09:00",
      "last_checked_at": "2026-05-14T16:14:39+09:00",
      "product_path": "products/bandai-gashapon-4549660760474000.json"
    },
    {
      "id": "bandai-gashapon-4549660760450000",
      "manufacturer_id": "bandai-gashapon",
      "manufacturer_name": "バンダイ ガシャポン",
      "brand_name": null,
      "series_name": null,
      "product_name": "最強ジャンプ２０２１年１２月号 ピーコックスパイダー",
      "release_year": 2021,
      "release_month": 11,
      "release_week": 1,
      "release_date": null,
      "preview_image_url": "https://bandai-a.akamaihd.net/bc/img/model/xl/1000166350_1.jpg",
      "preview_image_source_url": "https://gashapon.jp/products/detail.php?jan_code=4549660760450000",
      "price_yen": 300,
      "variant_count": 5,
      "jan_code": null,
      "official_url": "https://gashapon.jp/products/detail.php?jan_code=4549660760450000",
      "source_url": "https://gashapon.jp/products/detail.php?jan_code=4549660760450000",
      "first_detected_at": "2026-05-14T16:14:39+09:00",
      "last_checked_at": "2026-05-14T16:14:39+09:00",
      "product_path": "products/bandai-gashapon-4549660760450000.json"
    },
    {
      "id": "bandai-gashapon-4549660707813000",
      "manufacturer_id": "bandai-gashapon",
      "manufacturer_name": "バンダイ ガシャポン",
      "brand_name": null,
      "series_name": null,
      "product_name": "どうぶつサウナ5",
      "release_year": 2021,
      "release_month": 11,
      "release_week": 2,
      "release_date": null,
      "preview_image_url": "https://bandai-a.akamaihd.net/bc/img/model/xl/1000166015_1.jpg",
      "preview_image_source_url": "https://gashapon.jp/products/detail.php?jan_code=4549660707813000",
      "price_yen": 300,
      "variant_count": 5,
      "jan_code": null,
      "official_url": "https://gashapon.jp/products/detail.php?jan_code=4549660707813000",
      "source_url": "https://gashapon.jp/products/detail.php?jan_code=4549660707813000",
      "first_detected_at": "2026-05-14T16:14:39+09:00",
      "last_checked_at": "2026-05-14T16:14:39+09:00",
      "product_path": "products/bandai-gashapon-4549660707813000.json"
    },
    {
      "id": "bandai-gashapon-4549660630159000",
      "manufacturer_id": "bandai-gashapon",
      "manufacturer_name": "バンダイ ガシャポン",
      "brand_name": null,
      "series_name": null,
      "product_name": "アイドルマスター スターリットシーズン カプセルラバーマスコット",
      "release_year": 2021,
      "release_month": 11,
      "release_week": 2,
      "release_date": null,
      "preview_image_url": "https://bandai-a.akamaihd.net/bc/img/model/xl/1000166000_1.jpg",
      "preview_image_source_url": "https://gashapon.jp/products/detail.php?jan_code=4549660630159000",
      "price_yen": 300,
      "variant_count": 10,
      "jan_code": null,
      "official_url": "https://gashapon.jp/products/detail.php?jan_code=4549660630159000",
      "source_url": "https://gashapon.jp/products/detail.php?jan_code=4549660630159000",
      "first_detected_at": "2026-05-14T16:14:39+09:00",
      "last_checked_at": "2026-05-14T16:14:39+09:00",
      "product_path": "products/bandai-gashapon-4549660630159000.json"
    },
    {
      "id": "bandai-gashapon-4549660717454000",
      "manufacturer_id": "bandai-gashapon",
      "manufacturer_name": "バンダイ ガシャポン",
      "brand_name": null,
      "series_name": null,
      "product_name": "カプセルブーケ サンリオキャラクターズ２",
      "release_year": 2021,
      "release_month": 11,
      "release_week": 2,
      "release_date": null,
      "preview_image_url": "https://bandai-a.akamaihd.net/bc/img/model/xl/1000166005_1.jpg",
      "preview_image_source_url": "https://gashapon.jp/products/detail.php?jan_code=4549660717454000",
      "price_yen": 300,
      "variant_count": 4,
      "jan_code": null,
      "official_url": "https://gashapon.jp/products/detail.php?jan_code=4549660717454000",
      "source_url": "https://gashapon.jp/products/detail.php?jan_code=4549660717454000",
      "first_detected_at": "2026-05-14T16:14:39+09:00",
      "last_checked_at": "2026-05-14T16:14:39+09:00",
      "product_path": "products/bandai-gashapon-4549660717454000.json"
    },
    {
      "id": "bandai-gashapon-4549660717195000",
      "manufacturer_id": "bandai-gashapon",
      "manufacturer_name": "バンダイ ガシャポン",
      "brand_name": null,
      "series_name": null,
      "product_name": "ジョジョの奇妙な冒険 STAND×STAND 04",
      "release_year": 2021,
      "release_month": 11,
      "release_week": 2,
      "release_date": null,
      "preview_image_url": "https://bandai-a.akamaihd.net/bc/img/model/xl/1000165997_1.jpg",
      "preview_image_source_url": "https://gashapon.jp/products/detail.php?jan_code=4549660717195000",
      "price_yen": 300,
      "variant_count": 7,
      "jan_code": null,
      "official_url": "https://gashapon.jp/products/detail.php?jan_code=4549660717195000",
      "source_url": "https://gashapon.jp/products/detail.php?jan_code=4549660717195000",
      "first_detected_at": "2026-05-14T16:14:39+09:00",
      "last_checked_at": "2026-05-14T16:14:39+09:00",
      "product_path": "products/bandai-gashapon-4549660717195000.json"
    },
    {
      "id": "bandai-gashapon-4549660717294000",
      "manufacturer_id": "bandai-gashapon",
      "manufacturer_name": "バンダイ ガシャポン",
      "brand_name": null,
      "series_name": null,
      "product_name": "ドラえもん ならぶんです。",
      "release_year": 2021,
      "release_month": 11,
      "release_week": 2,
      "release_date": null,
      "preview_image_url": "https://bandai-a.akamaihd.net/bc/img/model/xl/1000165988_1.jpg",
      "preview_image_source_url": "https://gashapon.jp/products/detail.php?jan_code=4549660717294000",
      "price_yen": 300,
      "variant_count": 5,
      "jan_code": null,
      "official_url": "https://gashapon.jp/products/detail.php?jan_code=4549660717294000",
      "source_url": "https://gashapon.jp/products/detail.php?jan_code=4549660717294000",
      "first_detected_at": "2026-05-14T16:14:39+09:00",
      "last_checked_at": "2026-05-14T16:14:39+09:00",
      "product_path": "products/bandai-gashapon-4549660717294000.json"
    },
    {
      "id": "bandai-gashapon-4549660710233000",
      "manufacturer_id": "bandai-gashapon",
      "manufacturer_name": "バンダイ ガシャポン",
      "brand_name": null,
      "series_name": null,
      "product_name": "ハンコの反抗期",
      "release_year": 2021,
      "release_month": 11,
      "release_week": 2,
      "release_date": null,
      "preview_image_url": "https://bandai-a.akamaihd.net/bc/img/model/xl/1000164753_1.jpg",
      "preview_image_source_url": "https://gashapon.jp/products/detail.php?jan_code=4549660710233000",
      "price_yen": 300,
      "variant_count": 5,
      "jan_code": null,
      "official_url": "https://gashapon.jp/products/detail.php?jan_code=4549660710233000",
      "source_url": "https://gashapon.jp/products/detail.php?jan_code=4549660710233000",
      "first_detected_at": "2026-05-14T16:14:39+09:00",
      "last_checked_at": "2026-05-14T16:14:39+09:00",
      "product_path": "products/bandai-gashapon-4549660710233000.json"
    },
    {
      "id": "bandai-gashapon-4549660726432000",
      "manufacturer_id": "bandai-gashapon",
      "manufacturer_name": "バンダイ ガシャポン",
      "brand_name": null,
      "series_name": null,
      "product_name": "ロゴラバ スーパー戦隊シリーズvol.01",
      "release_year": 2021,
      "release_month": 11,
      "release_week": 2,
      "release_date": null,
      "preview_image_url": "https://bandai-a.akamaihd.net/bc/img/model/xl/1000165989_1.jpg",
      "preview_image_source_url": "https://gashapon.jp/products/detail.php?jan_code=4549660726432000",
      "price_yen": 300,
      "variant_count": 9,
      "jan_code": null,
      "official_url": "https://gashapon.jp/products/detail.php?jan_code=4549660726432000",
      "source_url": "https://gashapon.jp/products/detail.php?jan_code=4549660726432000",
      "first_detected_at": "2026-05-14T16:14:39+09:00",
      "last_checked_at": "2026-05-14T16:14:39+09:00",
      "product_path": "products/bandai-gashapon-4549660726432000.json"
    },
    {
      "id": "bandai-gashapon-4549660733515000",
      "manufacturer_id": "bandai-gashapon",
      "manufacturer_name": "バンダイ ガシャポン",
      "brand_name": null,
      "series_name": null,
      "product_name": "五等分の花嫁∬ カプセルラバーマスコット06",
      "release_year": 2021,
      "release_month": 11,
      "release_week": 2,
      "release_date": null,
      "preview_image_url": "https://bandai-a.akamaihd.net/bc/img/model/xl/1000165999_1.jpg",
      "preview_image_source_url": "https://gashapon.jp/products/detail.php?jan_code=4549660733515000",
      "price_yen": 300,
      "variant_count": 5,
      "jan_code": null,
      "official_url": "https://gashapon.jp/products/detail.php?jan_code=4549660733515000",
      "source_url": "https://gashapon.jp/products/detail.php?jan_code=4549660733515000",
      "first_detected_at": "2026-05-14T16:14:39+09:00",
      "last_checked_at": "2026-05-14T16:14:39+09:00",
      "product_path": "products/bandai-gashapon-4549660733515000.json"
    },
    {
      "id": "bandai-gashapon-4549660719656000",
      "manufacturer_id": "bandai-gashapon",
      "manufacturer_name": "バンダイ ガシャポン",
      "brand_name": null,
      "series_name": null,
      "product_name": "仮面ライダーリバイス バイスタンプゲノムサウンドシリーズ02",
      "release_year": 2021,
      "release_month": 11,
      "release_week": 2,
      "release_date": null,
      "preview_image_url": "https://bandai-a.akamaihd.net/bc/img/model/xl/1000165980_1.jpg",
      "preview_image_source_url": "https://gashapon.jp/products/detail.php?jan_code=4549660719656000",
      "price_yen": 400,
      "variant_count": 4,
      "jan_code": null,
      "official_url": "https://gashapon.jp/products/detail.php?jan_code=4549660719656000",
      "source_url": "https://gashapon.jp/products/detail.php?jan_code=4549660719656000",
      "first_detected_at": "2026-05-14T16:14:39+09:00",
      "last_checked_at": "2026-05-14T16:14:39+09:00",
      "product_path": "products/bandai-gashapon-4549660719656000.json"
    },
    {
      "id": "bandai-gashapon-4549660653851000",
      "manufacturer_id": "bandai-gashapon",
      "manufacturer_name": "バンダイ ガシャポン",
      "brand_name": null,
      "series_name": null,
      "product_name": "劇場版 ソードアート・オンライン -プログレッシブ-星なき夜のアリア あそーと",
      "release_year": 2021,
      "release_month": 11,
      "release_week": 2,
      "release_date": null,
      "preview_image_url": "https://bandai-a.akamaihd.net/bc/img/model/xl/1000165979_1.jpg",
      "preview_image_source_url": "https://gashapon.jp/products/detail.php?jan_code=4549660653851000",
      "price_yen": 300,
      "variant_count": 13,
      "jan_code": null,
      "official_url": "https://gashapon.jp/products/detail.php?jan_code=4549660653851000",
      "source_url": "https://gashapon.jp/products/detail.php?jan_code=4549660653851000",
      "first_detected_at": "2026-05-14T16:14:39+09:00",
      "last_checked_at": "2026-05-14T16:14:39+09:00",
      "product_path": "products/bandai-gashapon-4549660653851000.json"
    },
    {
      "id": "bandai-gashapon-4549660727057000",
      "manufacturer_id": "bandai-gashapon",
      "manufacturer_name": "バンダイ ガシャポン",
      "brand_name": null,
      "series_name": null,
      "product_name": "東京リベンジャーズ カプセルラバーマスコット２",
      "release_year": 2021,
      "release_month": 11,
      "release_week": 2,
      "release_date": null,
      "preview_image_url": "https://bandai-a.akamaihd.net/bc/img/model/xl/1000165998_1.jpg",
      "preview_image_source_url": "https://gashapon.jp/products/detail.php?jan_code=4549660727057000",
      "price_yen": 300,
      "variant_count": 9,
      "jan_code": null,
      "official_url": "https://gashapon.jp/products/detail.php?jan_code=4549660727057000",
      "source_url": "https://gashapon.jp/products/detail.php?jan_code=4549660727057000",
      "first_detected_at": "2026-05-14T16:14:39+09:00",
      "last_checked_at": "2026-05-14T16:14:39+09:00",
      "product_path": "products/bandai-gashapon-4549660727057000.json"
    },
    {
      "id": "bandai-gashapon-4549660708896000",
      "manufacturer_id": "bandai-gashapon",
      "manufacturer_name": "バンダイ ガシャポン",
      "brand_name": null,
      "series_name": null,
      "product_name": "鬼滅の刃 むにむにましゅまろますこっと４",
      "release_year": 2021,
      "release_month": 11,
      "release_week": 2,
      "release_date": null,
      "preview_image_url": "https://bandai-a.akamaihd.net/bc/img/model/xl/1000165995_1.jpg",
      "preview_image_source_url": "https://gashapon.jp/products/detail.php?jan_code=4549660708896000",
      "price_yen": 300,
      "variant_count": 5,
      "jan_code": null,
      "official_url": "https://gashapon.jp/products/detail.php?jan_code=4549660708896000",
      "source_url": "https://gashapon.jp/products/detail.php?jan_code=4549660708896000",
      "first_detected_at": "2026-05-14T16:14:39+09:00",
      "last_checked_at": "2026-05-14T16:14:39+09:00",
      "product_path": "products/bandai-gashapon-4549660708896000.json"
    },
    {
      "id": "bandai-gashapon-4549660717713000",
      "manufacturer_id": "bandai-gashapon",
      "manufacturer_name": "バンダイ ガシャポン",
      "brand_name": null,
      "series_name": null,
      "product_name": "IdentityⅤ 第五人格 カプセルラバーマスコット",
      "release_year": 2021,
      "release_month": 11,
      "release_week": 3,
      "release_date": null,
      "preview_image_url": "https://bandai-a.akamaihd.net/bc/img/model/xl/1000166031_1.jpg",
      "preview_image_source_url": "https://gashapon.jp/products/detail.php?jan_code=4549660717713000",
      "price_yen": 300,
      "variant_count": 10,
      "jan_code": null,
      "official_url": "https://gashapon.jp/products/detail.php?jan_code=4549660717713000",
      "source_url": "https://gashapon.jp/products/detail.php?jan_code=4549660717713000",
      "first_detected_at": "2026-05-14T16:14:39+09:00",
      "last_checked_at": "2026-05-14T16:14:39+09:00",
      "product_path": "products/bandai-gashapon-4549660717713000.json"
    },
    {
      "id": "bandai-gashapon-4549660717959000",
      "manufacturer_id": "bandai-gashapon",
      "manufacturer_name": "バンダイ ガシャポン",
      "brand_name": null,
      "series_name": null,
      "product_name": "Lipton Tea miniature charm-リプトンティーミニチュアチャーム-２",
      "release_year": 2021,
      "release_month": 11,
      "release_week": 3,
      "release_date": null,
      "preview_image_url": "https://bandai-a.akamaihd.net/bc/img/model/xl/1000165983_1.jpg",
      "preview_image_source_url": "https://gashapon.jp/products/detail.php?jan_code=4549660717959000",
      "price_yen": 200,
      "variant_count": 7,
      "jan_code": null,
      "official_url": "https://gashapon.jp/products/detail.php?jan_code=4549660717959000",
      "source_url": "https://gashapon.jp/products/detail.php?jan_code=4549660717959000",
      "first_detected_at": "2026-05-14T16:14:39+09:00",
      "last_checked_at": "2026-05-14T16:14:39+09:00",
      "product_path": "products/bandai-gashapon-4549660717959000.json"
    },
    {
      "id": "bandai-gashapon-4549660716532000",
      "manufacturer_id": "bandai-gashapon",
      "manufacturer_name": "バンダイ ガシャポン",
      "brand_name": null,
      "series_name": null,
      "product_name": "TVアニメ『ウマ娘 プリティーダービー Season 2』 全力疾走アクリルスタンド１",
      "release_year": 2021,
      "release_month": 11,
      "release_week": 3,
      "release_date": null,
      "preview_image_url": "https://bandai-a.akamaihd.net/bc/img/model/xl/1000166025_1.jpg",
      "preview_image_source_url": "https://gashapon.jp/products/detail.php?jan_code=4549660716532000",
      "price_yen": 400,
      "variant_count": 11,
      "jan_code": null,
      "official_url": "https://gashapon.jp/products/detail.php?jan_code=4549660716532000",
      "source_url": "https://gashapon.jp/products/detail.php?jan_code=4549660716532000",
      "first_detected_at": "2026-05-14T16:14:39+09:00",
      "last_checked_at": "2026-05-14T16:14:39+09:00",
      "product_path": "products/bandai-gashapon-4549660716532000.json"
    },
    {
      "id": "bandai-gashapon-4549660718338000",
      "manufacturer_id": "bandai-gashapon",
      "manufacturer_name": "バンダイ ガシャポン",
      "brand_name": null,
      "series_name": null,
      "product_name": "TVアニメ『ウマ娘 プリティーダービー Season 2』 全力疾走アクリルスタンド２",
      "release_year": 2021,
      "release_month": 11,
      "release_week": 3,
      "release_date": null,
      "preview_image_url": "https://bandai-a.akamaihd.net/bc/img/model/xl/1000166026_1.jpg",
      "preview_image_source_url": "https://gashapon.jp/products/detail.php?jan_code=4549660718338000",
      "price_yen": 400,
      "variant_count": 11,
      "jan_code": null,
      "official_url": "https://gashapon.jp/products/detail.php?jan_code=4549660718338000",
      "source_url": "https://gashapon.jp/products/detail.php?jan_code=4549660718338000",
      "first_detected_at": "2026-05-14T16:14:39+09:00",
      "last_checked_at": "2026-05-14T16:14:39+09:00",
      "product_path": "products/bandai-gashapon-4549660718338000.json"
    },
    {
      "id": "bandai-gashapon-4549660510598000",
      "manufacturer_id": "bandai-gashapon",
      "manufacturer_name": "バンダイ ガシャポン",
      "brand_name": null,
      "series_name": null,
      "product_name": "ごきげんぱんだ カプセルラバーマスコット",
      "release_year": 2021,
      "release_month": 11,
      "release_week": 3,
      "release_date": null,
      "preview_image_url": "https://bandai-a.akamaihd.net/bc/img/model/xl/1000155662_1.jpg",
      "preview_image_source_url": "https://gashapon.jp/products/detail.php?jan_code=4549660510598000",
      "price_yen": 300,
      "variant_count": 5,
      "jan_code": null,
      "official_url": "https://gashapon.jp/products/detail.php?jan_code=4549660510598000",
      "source_url": "https://gashapon.jp/products/detail.php?jan_code=4549660510598000",
      "first_detected_at": "2026-05-14T16:14:39+09:00",
      "last_checked_at": "2026-05-14T16:14:39+09:00",
      "product_path": "products/bandai-gashapon-4549660510598000.json"
    },
    {
      "id": "bandai-gashapon-4549660709114000",
      "manufacturer_id": "bandai-gashapon",
      "manufacturer_name": "バンダイ ガシャポン",
      "brand_name": null,
      "series_name": null,
      "product_name": "まいぜんシスターズ すいんぐマスコット",
      "release_year": 2021,
      "release_month": 11,
      "release_week": 3,
      "release_date": null,
      "preview_image_url": "https://bandai-a.akamaihd.net/bc/img/model/xl/1000166012_1.jpg",
      "preview_image_source_url": "https://gashapon.jp/products/detail.php?jan_code=4549660709114000",
      "price_yen": 300,
      "variant_count": 6,
      "jan_code": null,
      "official_url": "https://gashapon.jp/products/detail.php?jan_code=4549660709114000",
      "source_url": "https://gashapon.jp/products/detail.php?jan_code=4549660709114000",
      "first_detected_at": "2026-05-14T16:14:39+09:00",
      "last_checked_at": "2026-05-14T16:14:39+09:00",
      "product_path": "products/bandai-gashapon-4549660709114000.json"
    },
    {
      "id": "bandai-gashapon-4549660720034000",
      "manufacturer_id": "bandai-gashapon",
      "manufacturer_name": "バンダイ ガシャポン",
      "brand_name": null,
      "series_name": null,
      "product_name": "エリオスライジングヒーローズ カプセル缶バッジコレクションvol.4",
      "release_year": 2021,
      "release_month": 11,
      "release_week": 3,
      "release_date": null,
      "preview_image_url": "https://bandai-a.akamaihd.net/bc/img/model/xl/1000166002_1.jpg",
      "preview_image_source_url": "https://gashapon.jp/products/detail.php?jan_code=4549660720034000",
      "price_yen": 300,
      "variant_count": 8,
      "jan_code": null,
      "official_url": "https://gashapon.jp/products/detail.php?jan_code=4549660720034000",
      "source_url": "https://gashapon.jp/products/detail.php?jan_code=4549660720034000",
      "first_detected_at": "2026-05-14T16:14:39+09:00",
      "last_checked_at": "2026-05-14T16:14:39+09:00",
      "product_path": "products/bandai-gashapon-4549660720034000.json"
    },
    {
      "id": "bandai-gashapon-4549660377399000",
      "manufacturer_id": "bandai-gashapon",
      "manufacturer_name": "バンダイ ガシャポン",
      "brand_name": null,
      "series_name": null,
      "product_name": "カプキャラアニマル もふっと！ハムスター",
      "release_year": 2021,
      "release_month": 11,
      "release_week": 3,
      "release_date": null,
      "preview_image_url": "https://bandai-a.akamaihd.net/bc/img/model/xl/1000136844_1.jpg",
      "preview_image_source_url": "https://gashapon.jp/products/detail.php?jan_code=4549660377399000",
      "price_yen": 300,
      "variant_count": 6,
      "jan_code": null,
      "official_url": "https://gashapon.jp/products/detail.php?jan_code=4549660377399000",
      "source_url": "https://gashapon.jp/products/detail.php?jan_code=4549660377399000",
      "first_detected_at": "2026-05-14T16:14:39+09:00",
      "last_checked_at": "2026-05-14T16:14:39+09:00",
      "product_path": "products/bandai-gashapon-4549660377399000.json"
    },
    {
      "id": "bandai-gashapon-4549660707936000",
      "manufacturer_id": "bandai-gashapon",
      "manufacturer_name": "バンダイ ガシャポン",
      "brand_name": null,
      "series_name": null,
      "product_name": "テレワークの裏2",
      "release_year": 2021,
      "release_month": 11,
      "release_week": 3,
      "release_date": null,
      "preview_image_url": "https://bandai-a.akamaihd.net/bc/img/model/xl/1000166016_1.jpg",
      "preview_image_source_url": "https://gashapon.jp/products/detail.php?jan_code=4549660707936000",
      "price_yen": 300,
      "variant_count": 5,
      "jan_code": null,
      "official_url": "https://gashapon.jp/products/detail.php?jan_code=4549660707936000",
      "source_url": "https://gashapon.jp/products/detail.php?jan_code=4549660707936000",
      "first_detected_at": "2026-05-14T16:14:39+09:00",
      "last_checked_at": "2026-05-14T16:14:39+09:00",
      "product_path": "products/bandai-gashapon-4549660707936000.json"
    },
    {
      "id": "bandai-gashapon-4549660716396000",
      "manufacturer_id": "bandai-gashapon",
      "manufacturer_name": "バンダイ ガシャポン",
      "brand_name": null,
      "series_name": null,
      "product_name": "ラブライブ！虹ヶ咲学園スクールアイドル同好会 カプセルラバーマスコット06",
      "release_year": 2021,
      "release_month": 11,
      "release_week": 3,
      "release_date": null,
      "preview_image_url": "https://bandai-a.akamaihd.net/bc/img/model/xl/1000166001_1.jpg",
      "preview_image_source_url": "https://gashapon.jp/products/detail.php?jan_code=4549660716396000",
      "price_yen": 300,
      "variant_count": 13,
      "jan_code": null,
      "official_url": "https://gashapon.jp/products/detail.php?jan_code=4549660716396000",
      "source_url": "https://gashapon.jp/products/detail.php?jan_code=4549660716396000",
      "first_detected_at": "2026-05-14T16:14:39+09:00",
      "last_checked_at": "2026-05-14T16:14:39+09:00",
      "product_path": "products/bandai-gashapon-4549660716396000.json"
    },
    {
      "id": "bandai-gashapon-4549660508830000",
      "manufacturer_id": "bandai-gashapon",
      "manufacturer_name": "バンダイ ガシャポン",
      "brand_name": null,
      "series_name": null,
      "product_name": "明治シャカシャカチャーム",
      "release_year": 2021,
      "release_month": 11,
      "release_week": 3,
      "release_date": null,
      "preview_image_url": "https://bandai-a.akamaihd.net/bc/img/model/xl/1000148603_1.jpg",
      "preview_image_source_url": "https://gashapon.jp/products/detail.php?jan_code=4549660508830000",
      "price_yen": 200,
      "variant_count": 6,
      "jan_code": null,
      "official_url": "https://gashapon.jp/products/detail.php?jan_code=4549660508830000",
      "source_url": "https://gashapon.jp/products/detail.php?jan_code=4549660508830000",
      "first_detected_at": "2026-05-14T16:14:39+09:00",
      "last_checked_at": "2026-05-14T16:14:39+09:00",
      "product_path": "products/bandai-gashapon-4549660508830000.json"
    },
    {
      "id": "bandai-gashapon-4549660721079000",
      "manufacturer_id": "bandai-gashapon",
      "manufacturer_name": "バンダイ ガシャポン",
      "brand_name": null,
      "series_name": null,
      "product_name": "TVアニメ『ウマ娘 プリティーダービー Season 2』 ダービーラバーマスコット",
      "release_year": 2021,
      "release_month": 11,
      "release_week": 4,
      "release_date": null,
      "preview_image_url": "https://bandai-a.akamaihd.net/bc/img/model/xl/1000166024_1.jpg",
      "preview_image_source_url": "https://gashapon.jp/products/detail.php?jan_code=4549660721079000",
      "price_yen": 300,
      "variant_count": 10,
      "jan_code": null,
      "official_url": "https://gashapon.jp/products/detail.php?jan_code=4549660721079000",
      "source_url": "https://gashapon.jp/products/detail.php?jan_code=4549660721079000",
      "first_detected_at": "2026-05-14T16:14:39+09:00",
      "last_checked_at": "2026-05-14T16:14:39+09:00",
      "product_path": "products/bandai-gashapon-4549660721079000.json"
    },
    {
      "id": "bandai-gashapon-4549660748274000",
      "manufacturer_id": "bandai-gashapon",
      "manufacturer_name": "バンダイ ガシャポン",
      "brand_name": null,
      "series_name": null,
      "product_name": "【箱売】ミニチュア ルーレット式おみくじ器",
      "release_year": 2021,
      "release_month": 11,
      "release_week": 4,
      "release_date": null,
      "preview_image_url": "https://bandai-a.akamaihd.net/bc/img/model/xl/1000166027_1.jpg",
      "preview_image_source_url": "https://gashapon.jp/products/detail.php?jan_code=4549660748274000",
      "price_yen": 440,
      "variant_count": 3,
      "jan_code": null,
      "official_url": "https://gashapon.jp/products/detail.php?jan_code=4549660748274000",
      "source_url": "https://gashapon.jp/products/detail.php?jan_code=4549660748274000",
      "first_detected_at": "2026-05-14T16:14:39+09:00",
      "last_checked_at": "2026-05-14T16:14:39+09:00",
      "product_path": "products/bandai-gashapon-4549660748274000.json"
    },
    {
      "id": "bandai-gashapon-4549660719991000",
      "manufacturer_id": "bandai-gashapon",
      "manufacturer_name": "バンダイ ガシャポン",
      "brand_name": null,
      "series_name": null,
      "product_name": "おいしいぬいちゃん ～ふかふかぱん～",
      "release_year": 2021,
      "release_month": 11,
      "release_week": 4,
      "release_date": null,
      "preview_image_url": "https://bandai-a.akamaihd.net/bc/img/model/xl/1000166003_1.jpg",
      "preview_image_source_url": "https://gashapon.jp/products/detail.php?jan_code=4549660719991000",
      "price_yen": 300,
      "variant_count": 5,
      "jan_code": null,
      "official_url": "https://gashapon.jp/products/detail.php?jan_code=4549660719991000",
      "source_url": "https://gashapon.jp/products/detail.php?jan_code=4549660719991000",
      "first_detected_at": "2026-05-14T16:14:39+09:00",
      "last_checked_at": "2026-05-14T16:14:39+09:00",
      "product_path": "products/bandai-gashapon-4549660719991000.json"
    },
    {
      "id": "bandai-gashapon-4549660727156000",
      "manufacturer_id": "bandai-gashapon",
      "manufacturer_name": "バンダイ ガシャポン",
      "brand_name": null,
      "series_name": null,
      "product_name": "それいけ！アンパンマン ぴょこぴょこアンパンマン5",
      "release_year": 2021,
      "release_month": 11,
      "release_week": 4,
      "release_date": null,
      "preview_image_url": "https://bandai-a.akamaihd.net/bc/img/model/xl/1000165985_1.jpg",
      "preview_image_source_url": "https://gashapon.jp/products/detail.php?jan_code=4549660727156000",
      "price_yen": 300,
      "variant_count": 5,
      "jan_code": null,
      "official_url": "https://gashapon.jp/products/detail.php?jan_code=4549660727156000",
      "source_url": "https://gashapon.jp/products/detail.php?jan_code=4549660727156000",
      "first_detected_at": "2026-05-14T16:14:39+09:00",
      "last_checked_at": "2026-05-14T16:14:39+09:00",
      "product_path": "products/bandai-gashapon-4549660727156000.json"
    },
    {
      "id": "bandai-gashapon-4549660727552000",
      "manufacturer_id": "bandai-gashapon",
      "manufacturer_name": "バンダイ ガシャポン",
      "brand_name": null,
      "series_name": null,
      "product_name": "はぐこっとーと ミッキーマウス アニバーサリー",
      "release_year": 2021,
      "release_month": 11,
      "release_week": 4,
      "release_date": null,
      "preview_image_url": "https://bandai-a.akamaihd.net/bc/img/model/xl/1000166022_1.jpg",
      "preview_image_source_url": "https://gashapon.jp/products/detail.php?jan_code=4549660727552000",
      "price_yen": 500,
      "variant_count": 3,
      "jan_code": null,
      "official_url": "https://gashapon.jp/products/detail.php?jan_code=4549660727552000",
      "source_url": "https://gashapon.jp/products/detail.php?jan_code=4549660727552000",
      "first_detected_at": "2026-05-14T16:14:39+09:00",
      "last_checked_at": "2026-05-14T16:14:39+09:00",
      "product_path": "products/bandai-gashapon-4549660727552000.json"
    },
    {
      "id": "bandai-gashapon-4549660708513000",
      "manufacturer_id": "bandai-gashapon",
      "manufacturer_name": "バンダイ ガシャポン",
      "brand_name": null,
      "series_name": null,
      "product_name": "めじるしアクセサリー ヨッシースタンプ",
      "release_year": 2021,
      "release_month": 11,
      "release_week": 4,
      "release_date": null,
      "preview_image_url": "https://bandai-a.akamaihd.net/bc/img/model/xl/1000165984_1.jpg",
      "preview_image_source_url": "https://gashapon.jp/products/detail.php?jan_code=4549660708513000",
      "price_yen": 200,
      "variant_count": 8,
      "jan_code": null,
      "official_url": "https://gashapon.jp/products/detail.php?jan_code=4549660708513000",
      "source_url": "https://gashapon.jp/products/detail.php?jan_code=4549660708513000",
      "first_detected_at": "2026-05-14T16:14:39+09:00",
      "last_checked_at": "2026-05-14T16:14:39+09:00",
      "product_path": "products/bandai-gashapon-4549660708513000.json"
    },
    {
      "id": "bandai-gashapon-4549660717775000",
      "manufacturer_id": "bandai-gashapon",
      "manufacturer_name": "バンダイ ガシャポン",
      "brand_name": null,
      "series_name": null,
      "product_name": "カプキャラ にゃんこ大戦争４",
      "release_year": 2021,
      "release_month": 11,
      "release_week": 4,
      "release_date": null,
      "preview_image_url": "https://bandai-a.akamaihd.net/bc/img/model/xl/1000166011_1.jpg",
      "preview_image_source_url": "https://gashapon.jp/products/detail.php?jan_code=4549660717775000",
      "price_yen": 300,
      "variant_count": 5,
      "jan_code": null,
      "official_url": "https://gashapon.jp/products/detail.php?jan_code=4549660717775000",
      "source_url": "https://gashapon.jp/products/detail.php?jan_code=4549660717775000",
      "first_detected_at": "2026-05-14T16:14:39+09:00",
      "last_checked_at": "2026-05-14T16:14:39+09:00",
      "product_path": "products/bandai-gashapon-4549660717775000.json"
    },
    {
      "id": "bandai-gashapon-4549660608592000",
      "manufacturer_id": "bandai-gashapon",
      "manufacturer_name": "バンダイ ガシャポン",
      "brand_name": null,
      "series_name": null,
      "product_name": "コレキャラ！ MARVEL アイアンマン アーマーコレクション01",
      "release_year": 2021,
      "release_month": 11,
      "release_week": 4,
      "release_date": null,
      "preview_image_url": "https://bandai-a.akamaihd.net/bc/img/model/xl/1000166004_1.jpg",
      "preview_image_source_url": "https://gashapon.jp/products/detail.php?jan_code=4549660608592000",
      "price_yen": 300,
      "variant_count": 7,
      "jan_code": null,
      "official_url": "https://gashapon.jp/products/detail.php?jan_code=4549660608592000",
      "source_url": "https://gashapon.jp/products/detail.php?jan_code=4549660608592000",
      "first_detected_at": "2026-05-14T16:14:39+09:00",
      "last_checked_at": "2026-05-14T16:14:39+09:00",
      "product_path": "products/bandai-gashapon-4549660608592000.json"
    },
    {
      "id": "bandai-gashapon-4549660608691000",
      "manufacturer_id": "bandai-gashapon",
      "manufacturer_name": "バンダイ ガシャポン",
      "brand_name": null,
      "series_name": null,
      "product_name": "ミニチュア ルーレット式おみくじ器",
      "release_year": 2021,
      "release_month": 11,
      "release_week": 4,
      "release_date": null,
      "preview_image_url": "https://bandai-a.akamaihd.net/bc/img/model/xl/1000158403_1.jpg",
      "preview_image_source_url": "https://gashapon.jp/products/detail.php?jan_code=4549660608691000",
      "price_yen": 400,
      "variant_count": 3,
      "jan_code": null,
      "official_url": "https://gashapon.jp/products/detail.php?jan_code=4549660608691000",
      "source_url": "https://gashapon.jp/products/detail.php?jan_code=4549660608691000",
      "first_detected_at": "2026-05-14T16:14:39+09:00",
      "last_checked_at": "2026-05-14T16:14:39+09:00",
      "product_path": "products/bandai-gashapon-4549660608691000.json"
    },
    {
      "id": "bandai-gashapon-4549660719717000",
      "manufacturer_id": "bandai-gashapon",
      "manufacturer_name": "バンダイ ガシャポン",
      "brand_name": null,
      "series_name": null,
      "product_name": "仮面ライダーシリーズ 変身ベルトピンズコレクション03",
      "release_year": 2021,
      "release_month": 11,
      "release_week": 4,
      "release_date": null,
      "preview_image_url": "https://bandai-a.akamaihd.net/bc/img/model/xl/1000165990_1.jpg",
      "preview_image_source_url": "https://gashapon.jp/products/detail.php?jan_code=4549660719717000",
      "price_yen": 300,
      "variant_count": 5,
      "jan_code": null,
      "official_url": "https://gashapon.jp/products/detail.php?jan_code=4549660719717000",
      "source_url": "https://gashapon.jp/products/detail.php?jan_code=4549660719717000",
      "first_detected_at": "2026-05-14T16:14:39+09:00",
      "last_checked_at": "2026-05-14T16:14:39+09:00",
      "product_path": "products/bandai-gashapon-4549660719717000.json"
    },
    {
      "id": "bandai-gashapon-4549660719694000",
      "manufacturer_id": "bandai-gashapon",
      "manufacturer_name": "バンダイ ガシャポン",
      "brand_name": null,
      "series_name": null,
      "product_name": "仮面ライダーリバイス リバイスギアコレクション02",
      "release_year": 2021,
      "release_month": 11,
      "release_week": 4,
      "release_date": null,
      "preview_image_url": "https://bandai-a.akamaihd.net/bc/img/model/xl/1000165982_1.jpg",
      "preview_image_source_url": "https://gashapon.jp/products/detail.php?jan_code=4549660719694000",
      "price_yen": 200,
      "variant_count": 7,
      "jan_code": null,
      "official_url": "https://gashapon.jp/products/detail.php?jan_code=4549660719694000",
      "source_url": "https://gashapon.jp/products/detail.php?jan_code=4549660719694000",
      "first_detected_at": "2026-05-14T16:14:39+09:00",
      "last_checked_at": "2026-05-14T16:14:39+09:00",
      "product_path": "products/bandai-gashapon-4549660719694000.json"
    },
    {
      "id": "bandai-gashapon-4549660653455000",
      "manufacturer_id": "bandai-gashapon",
      "manufacturer_name": "バンダイ ガシャポン",
      "brand_name": null,
      "series_name": null,
      "product_name": "呪術廻戦 HGシリーズ01",
      "release_year": 2021,
      "release_month": 11,
      "release_week": 4,
      "release_date": null,
      "preview_image_url": "https://bandai-a.akamaihd.net/bc/img/model/xl/1000166020_1.jpg",
      "preview_image_source_url": "https://gashapon.jp/products/detail.php?jan_code=4549660653455000",
      "price_yen": 500,
      "variant_count": 4,
      "jan_code": null,
      "official_url": "https://gashapon.jp/products/detail.php?jan_code=4549660653455000",
      "source_url": "https://gashapon.jp/products/detail.php?jan_code=4549660653455000",
      "first_detected_at": "2026-05-14T16:14:39+09:00",
      "last_checked_at": "2026-05-14T16:14:39+09:00",
      "product_path": "products/bandai-gashapon-4549660653455000.json"
    },
    {
      "id": "bandai-gashapon-4549660721550000",
      "manufacturer_id": "bandai-gashapon",
      "manufacturer_name": "バンダイ ガシャポン",
      "brand_name": null,
      "series_name": null,
      "product_name": "呪術廻戦 アクリルスタンド０２",
      "release_year": 2021,
      "release_month": 11,
      "release_week": 4,
      "release_date": null,
      "preview_image_url": "https://bandai-a.akamaihd.net/bc/img/model/xl/1000166352_1.jpg",
      "preview_image_source_url": "https://gashapon.jp/products/detail.php?jan_code=4549660721550000",
      "price_yen": 400,
      "variant_count": 8,
      "jan_code": null,
      "official_url": "https://gashapon.jp/products/detail.php?jan_code=4549660721550000",
      "source_url": "https://gashapon.jp/products/detail.php?jan_code=4549660721550000",
      "first_detected_at": "2026-05-14T16:14:39+09:00",
      "last_checked_at": "2026-05-14T16:14:39+09:00",
      "product_path": "products/bandai-gashapon-4549660721550000.json"
    },
    {
      "id": "bandai-gashapon-4549660716839000",
      "manufacturer_id": "bandai-gashapon",
      "manufacturer_name": "バンダイ ガシャポン",
      "brand_name": null,
      "series_name": null,
      "product_name": "呪術廻戦 カプセルラバーマスコット04",
      "release_year": 2021,
      "release_month": 11,
      "release_week": 4,
      "release_date": null,
      "preview_image_url": "https://bandai-a.akamaihd.net/bc/img/model/xl/1000165996_1.jpg",
      "preview_image_source_url": "https://gashapon.jp/products/detail.php?jan_code=4549660716839000",
      "price_yen": 300,
      "variant_count": 11,
      "jan_code": null,
      "official_url": "https://gashapon.jp/products/detail.php?jan_code=4549660716839000",
      "source_url": "https://gashapon.jp/products/detail.php?jan_code=4549660716839000",
      "first_detected_at": "2026-05-14T16:14:39+09:00",
      "last_checked_at": "2026-05-14T16:14:39+09:00",
      "product_path": "products/bandai-gashapon-4549660716839000.json"
    },
    {
      "id": "bandai-gashapon-4549660660798000",
      "manufacturer_id": "bandai-gashapon",
      "manufacturer_name": "バンダイ ガシャポン",
      "brand_name": null,
      "series_name": null,
      "product_name": "地縛少年花子くん カプセルラバーマスコット～Name Collection～",
      "release_year": 2021,
      "release_month": 11,
      "release_week": 4,
      "release_date": null,
      "preview_image_url": "https://bandai-a.akamaihd.net/bc/img/model/xl/1000166014_1.jpg",
      "preview_image_source_url": "https://gashapon.jp/products/detail.php?jan_code=4549660660798000",
      "price_yen": 300,
      "variant_count": 7,
      "jan_code": null,
      "official_url": "https://gashapon.jp/products/detail.php?jan_code=4549660660798000",
      "source_url": "https://gashapon.jp/products/detail.php?jan_code=4549660660798000",
      "first_detected_at": "2026-05-14T16:14:39+09:00",
      "last_checked_at": "2026-05-14T16:14:39+09:00",
      "product_path": "products/bandai-gashapon-4549660660798000.json"
    },
    {
      "id": "bandai-gashapon-4549660721758000",
      "manufacturer_id": "bandai-gashapon",
      "manufacturer_name": "バンダイ ガシャポン",
      "brand_name": null,
      "series_name": null,
      "product_name": "日本の銘酒 SAKE COLLECTION２",
      "release_year": 2021,
      "release_month": 11,
      "release_week": 4,
      "release_date": null,
      "preview_image_url": "https://bandai-a.akamaihd.net/bc/img/model/xl/1000166018_1.jpg",
      "preview_image_source_url": "https://gashapon.jp/products/detail.php?jan_code=4549660721758000",
      "price_yen": 300,
      "variant_count": 6,
      "jan_code": null,
      "official_url": "https://gashapon.jp/products/detail.php?jan_code=4549660721758000",
      "source_url": "https://gashapon.jp/products/detail.php?jan_code=4549660721758000",
      "first_detected_at": "2026-05-14T16:14:39+09:00",
      "last_checked_at": "2026-05-14T16:14:39+09:00",
      "product_path": "products/bandai-gashapon-4549660721758000.json"
    },
    {
      "id": "bandai-gashapon-4549660722076000",
      "manufacturer_id": "bandai-gashapon",
      "manufacturer_name": "バンダイ ガシャポン",
      "brand_name": null,
      "series_name": null,
      "product_name": "BT21 カプセルラバーマスコット ～BABY SLEEPING TIME～",
      "release_year": 2021,
      "release_month": 11,
      "release_week": 5,
      "release_date": null,
      "preview_image_url": "https://bandai-a.akamaihd.net/bc/img/model/xl/1000167322_1.jpg",
      "preview_image_source_url": "https://gashapon.jp/products/detail.php?jan_code=4549660722076000",
      "price_yen": 300,
      "variant_count": 7,
      "jan_code": null,
      "official_url": "https://gashapon.jp/products/detail.php?jan_code=4549660722076000",
      "source_url": "https://gashapon.jp/products/detail.php?jan_code=4549660722076000",
      "first_detected_at": "2026-05-14T16:14:39+09:00",
      "last_checked_at": "2026-05-14T16:14:39+09:00",
      "product_path": "products/bandai-gashapon-4549660722076000.json"
    },
    {
      "id": "bandai-gashapon-4549660719779000",
      "manufacturer_id": "bandai-gashapon",
      "manufacturer_name": "バンダイ ガシャポン",
      "brand_name": null,
      "series_name": null,
      "product_name": "GPシャドウアート ウルトラマン",
      "release_year": 2021,
      "release_month": 11,
      "release_week": 5,
      "release_date": null,
      "preview_image_url": "https://bandai-a.akamaihd.net/bc/img/model/xl/1000165992_1.jpg",
      "preview_image_source_url": "https://gashapon.jp/products/detail.php?jan_code=4549660719779000",
      "price_yen": 300,
      "variant_count": 5,
      "jan_code": null,
      "official_url": "https://gashapon.jp/products/detail.php?jan_code=4549660719779000",
      "source_url": "https://gashapon.jp/products/detail.php?jan_code=4549660719779000",
      "first_detected_at": "2026-05-14T16:14:39+09:00",
      "last_checked_at": "2026-05-14T16:14:39+09:00",
      "product_path": "products/bandai-gashapon-4549660719779000.json"
    },
    {
      "id": "bandai-gashapon-4549660661337000",
      "manufacturer_id": "bandai-gashapon",
      "manufacturer_name": "バンダイ ガシャポン",
      "brand_name": null,
      "series_name": null,
      "product_name": "Ringcolle! 大玉たこ焼きリング ゆびたこ！",
      "release_year": 2021,
      "release_month": 11,
      "release_week": 5,
      "release_date": null,
      "preview_image_url": "https://bandai-a.akamaihd.net/bc/img/model/xl/1000160879_1.jpg",
      "preview_image_source_url": "https://gashapon.jp/products/detail.php?jan_code=4549660661337000",
      "price_yen": 300,
      "variant_count": 5,
      "jan_code": null,
      "official_url": "https://gashapon.jp/products/detail.php?jan_code=4549660661337000",
      "source_url": "https://gashapon.jp/products/detail.php?jan_code=4549660661337000",
      "first_detected_at": "2026-05-14T16:14:39+09:00",
      "last_checked_at": "2026-05-14T16:14:39+09:00",
      "product_path": "products/bandai-gashapon-4549660661337000.json"
    },
    {
      "id": "bandai-gashapon-4549660717232000",
      "manufacturer_id": "bandai-gashapon",
      "manufacturer_name": "バンダイ ガシャポン",
      "brand_name": null,
      "series_name": null,
      "product_name": "ことりんぐ２",
      "release_year": 2021,
      "release_month": 11,
      "release_week": 5,
      "release_date": null,
      "preview_image_url": "https://bandai-a.akamaihd.net/bc/img/model/xl/1000166017_1.jpg",
      "preview_image_source_url": "https://gashapon.jp/products/detail.php?jan_code=4549660717232000",
      "price_yen": 300,
      "variant_count": 6,
      "jan_code": null,
      "official_url": "https://gashapon.jp/products/detail.php?jan_code=4549660717232000",
      "source_url": "https://gashapon.jp/products/detail.php?jan_code=4549660717232000",
      "first_detected_at": "2026-05-14T16:14:39+09:00",
      "last_checked_at": "2026-05-14T16:14:39+09:00",
      "product_path": "products/bandai-gashapon-4549660717232000.json"
    },
    {
      "id": "bandai-gashapon-4549660708759000",
      "manufacturer_id": "bandai-gashapon",
      "manufacturer_name": "バンダイ ガシャポン",
      "brand_name": null,
      "series_name": null,
      "product_name": "しゅごキャラ！ PEACH-PIT 20th Special カプセルラバーマスコット",
      "release_year": 2021,
      "release_month": 11,
      "release_week": 5,
      "release_date": null,
      "preview_image_url": "https://bandai-a.akamaihd.net/bc/img/model/xl/1000166019_1.jpg",
      "preview_image_source_url": "https://gashapon.jp/products/detail.php?jan_code=4549660708759000",
      "price_yen": 300,
      "variant_count": 6,
      "jan_code": null,
      "official_url": "https://gashapon.jp/products/detail.php?jan_code=4549660708759000",
      "source_url": "https://gashapon.jp/products/detail.php?jan_code=4549660708759000",
      "first_detected_at": "2026-05-14T16:14:39+09:00",
      "last_checked_at": "2026-05-14T16:14:39+09:00",
      "product_path": "products/bandai-gashapon-4549660708759000.json"
    },
    {
      "id": "bandai-gashapon-4549660630555000",
      "manufacturer_id": "bandai-gashapon",
      "manufacturer_name": "バンダイ ガシャポン",
      "brand_name": null,
      "series_name": null,
      "product_name": "ゆるキャン△ ゆるキャン△あそーと",
      "release_year": 2021,
      "release_month": 11,
      "release_week": 5,
      "release_date": null,
      "preview_image_url": "https://bandai-a.akamaihd.net/bc/img/model/xl/1000160878_1.jpg",
      "preview_image_source_url": "https://gashapon.jp/products/detail.php?jan_code=4549660630555000",
      "price_yen": 300,
      "variant_count": 14,
      "jan_code": null,
      "official_url": "https://gashapon.jp/products/detail.php?jan_code=4549660630555000",
      "source_url": "https://gashapon.jp/products/detail.php?jan_code=4549660630555000",
      "first_detected_at": "2026-05-14T16:14:39+09:00",
      "last_checked_at": "2026-05-14T16:14:39+09:00",
      "product_path": "products/bandai-gashapon-4549660630555000.json"
    },
    {
      "id": "bandai-gashapon-4549660589518000",
      "manufacturer_id": "bandai-gashapon",
      "manufacturer_name": "バンダイ ガシャポン",
      "brand_name": null,
      "series_name": null,
      "product_name": "ガラピコぷ～ おっきないないいないばあったまご",
      "release_year": 2021,
      "release_month": 11,
      "release_week": 5,
      "release_date": null,
      "preview_image_url": "https://bandai-a.akamaihd.net/bc/img/model/xl/1000166030_1.jpg",
      "preview_image_source_url": "https://gashapon.jp/products/detail.php?jan_code=4549660589518000",
      "price_yen": 300,
      "variant_count": 3,
      "jan_code": null,
      "official_url": "https://gashapon.jp/products/detail.php?jan_code=4549660589518000",
      "source_url": "https://gashapon.jp/products/detail.php?jan_code=4549660589518000",
      "first_detected_at": "2026-05-14T16:14:39+09:00",
      "last_checked_at": "2026-05-14T16:14:39+09:00",
      "product_path": "products/bandai-gashapon-4549660589518000.json"
    },
    {
      "id": "bandai-gashapon-4549660716754000",
      "manufacturer_id": "bandai-gashapon",
      "manufacturer_name": "バンダイ ガシャポン",
      "brand_name": null,
      "series_name": null,
      "product_name": "クレヨンしんちゃん チョコビケース",
      "release_year": 2021,
      "release_month": 11,
      "release_week": 5,
      "release_date": null,
      "preview_image_url": "https://bandai-a.akamaihd.net/bc/img/model/xl/1000165994_1.jpg",
      "preview_image_source_url": "https://gashapon.jp/products/detail.php?jan_code=4549660716754000",
      "price_yen": 300,
      "variant_count": 5,
      "jan_code": null,
      "official_url": "https://gashapon.jp/products/detail.php?jan_code=4549660716754000",
      "source_url": "https://gashapon.jp/products/detail.php?jan_code=4549660716754000",
      "first_detected_at": "2026-05-14T16:14:39+09:00",
      "last_checked_at": "2026-05-14T16:14:39+09:00",
      "product_path": "products/bandai-gashapon-4549660716754000.json"
    },
    {
      "id": "bandai-gashapon-4549660501695000",
      "manufacturer_id": "bandai-gashapon",
      "manufacturer_name": "バンダイ ガシャポン",
      "brand_name": null,
      "series_name": null,
      "product_name": "ジョジョの奇妙な冒険 カプセルフィギュアコレクション03",
      "release_year": 2021,
      "release_month": 11,
      "release_week": 5,
      "release_date": null,
      "preview_image_url": "https://bandai-a.akamaihd.net/bc/img/model/xl/1000146353_1.jpg",
      "preview_image_source_url": "https://gashapon.jp/products/detail.php?jan_code=4549660501695000",
      "price_yen": 400,
      "variant_count": 7,
      "jan_code": null,
      "official_url": "https://gashapon.jp/products/detail.php?jan_code=4549660501695000",
      "source_url": "https://gashapon.jp/products/detail.php?jan_code=4549660501695000",
      "first_detected_at": "2026-05-14T16:14:39+09:00",
      "last_checked_at": "2026-05-14T16:14:39+09:00",
      "product_path": "products/bandai-gashapon-4549660501695000.json"
    },
    {
      "id": "bandai-gashapon-4549660695691000",
      "manufacturer_id": "bandai-gashapon",
      "manufacturer_name": "バンダイ ガシャポン",
      "brand_name": null,
      "series_name": null,
      "product_name": "トロピカル～ジュ！プリキュア プリキュアトロピカルシャイニーボックス",
      "release_year": 2021,
      "release_month": 11,
      "release_week": 5,
      "release_date": null,
      "preview_image_url": "https://bandai-a.akamaihd.net/bc/img/model/xl/1000165987_1.jpg",
      "preview_image_source_url": "https://gashapon.jp/products/detail.php?jan_code=4549660695691000",
      "price_yen": 300,
      "variant_count": 5,
      "jan_code": null,
      "official_url": "https://gashapon.jp/products/detail.php?jan_code=4549660695691000",
      "source_url": "https://gashapon.jp/products/detail.php?jan_code=4549660695691000",
      "first_detected_at": "2026-05-14T16:14:39+09:00",
      "last_checked_at": "2026-05-14T16:14:39+09:00",
      "product_path": "products/bandai-gashapon-4549660695691000.json"
    },
    {
      "id": "bandai-gashapon-4549660696117000",
      "manufacturer_id": "bandai-gashapon",
      "manufacturer_name": "バンダイ ガシャポン",
      "brand_name": null,
      "series_name": null,
      "product_name": "ポケットモンスター プカプカ浮き輪コレクション２",
      "release_year": 2021,
      "release_month": 11,
      "release_week": 5,
      "release_date": null,
      "preview_image_url": "https://bandai-a.akamaihd.net/bc/img/model/xl/1000165978_1.jpg",
      "preview_image_source_url": "https://gashapon.jp/products/detail.php?jan_code=4549660696117000",
      "price_yen": 300,
      "variant_count": 5,
      "jan_code": null,
      "official_url": "https://gashapon.jp/products/detail.php?jan_code=4549660696117000",
      "source_url": "https://gashapon.jp/products/detail.php?jan_code=4549660696117000",
      "first_detected_at": "2026-05-14T16:14:39+09:00",
      "last_checked_at": "2026-05-14T16:14:39+09:00",
      "product_path": "products/bandai-gashapon-4549660696117000.json"
    },
    {
      "id": "bandai-gashapon-4549660715627000",
      "manufacturer_id": "bandai-gashapon",
      "manufacturer_name": "バンダイ ガシャポン",
      "brand_name": null,
      "series_name": null,
      "product_name": "仮面ライダーリバイス サウンド変身ベルトPREMIUM リバイスドライバー",
      "release_year": 2021,
      "release_month": 11,
      "release_week": 5,
      "release_date": null,
      "preview_image_url": "https://bandai-a.akamaihd.net/bc/img/model/xl/1000166023_1.jpg",
      "preview_image_source_url": "https://gashapon.jp/products/detail.php?jan_code=4549660715627000",
      "price_yen": 1500,
      "variant_count": 1,
      "jan_code": null,
      "official_url": "https://gashapon.jp/products/detail.php?jan_code=4549660715627000",
      "source_url": "https://gashapon.jp/products/detail.php?jan_code=4549660715627000",
      "first_detected_at": "2026-05-14T16:14:39+09:00",
      "last_checked_at": "2026-05-14T16:14:39+09:00",
      "product_path": "products/bandai-gashapon-4549660715627000.json"
    },
    {
      "id": "bandai-gashapon-4549660653479000",
      "manufacturer_id": "bandai-gashapon",
      "manufacturer_name": "バンダイ ガシャポン",
      "brand_name": null,
      "series_name": null,
      "product_name": "呪術廻戦 カプセルフィギュアコレクション03",
      "release_year": 2021,
      "release_month": 11,
      "release_week": 5,
      "release_date": null,
      "preview_image_url": "https://bandai-a.akamaihd.net/bc/img/model/xl/1000165981_1.jpg",
      "preview_image_source_url": "https://gashapon.jp/products/detail.php?jan_code=4549660653479000",
      "price_yen": 400,
      "variant_count": 7,
      "jan_code": null,
      "official_url": "https://gashapon.jp/products/detail.php?jan_code=4549660653479000",
      "source_url": "https://gashapon.jp/products/detail.php?jan_code=4549660653479000",
      "first_detected_at": "2026-05-14T16:14:39+09:00",
      "last_checked_at": "2026-05-14T16:14:39+09:00",
      "product_path": "products/bandai-gashapon-4549660653479000.json"
    },
    {
      "id": "bandai-gashapon-4549660109099000",
      "manufacturer_id": "bandai-gashapon",
      "manufacturer_name": "バンダイ ガシャポン",
      "brand_name": null,
      "series_name": null,
      "product_name": "機動戦士ガンダム MOBILE SUIT ENSEMBLE 01",
      "release_year": 2021,
      "release_month": 11,
      "release_week": 5,
      "release_date": null,
      "preview_image_url": "https://bandai-a.akamaihd.net/bc/img/model/xl/1000110779_1.jpg",
      "preview_image_source_url": "https://gashapon.jp/products/detail.php?jan_code=4549660109099000",
      "price_yen": 500,
      "variant_count": 5,
      "jan_code": null,
      "official_url": "https://gashapon.jp/products/detail.php?jan_code=4549660109099000",
      "source_url": "https://gashapon.jp/products/detail.php?jan_code=4549660109099000",
      "first_detected_at": "2026-05-14T16:14:39+09:00",
      "last_checked_at": "2026-05-14T16:14:39+09:00",
      "product_path": "products/bandai-gashapon-4549660109099000.json"
    },
    {
      "id": "kitanclub-tokidokisofubi",
      "manufacturer_id": "kitanclub",
      "manufacturer_name": "キタンクラブ",
      "brand_name": null,
      "series_name": null,
      "product_name": "tokidoki ソフビコレクション",
      "release_year": 2021,
      "release_month": 11,
      "release_week": null,
      "release_date": null,
      "preview_image_url": "https://kitan.jp/wp-content/uploads/2021/11/tokidoki_sofbi_DP-1-1.jpg",
      "preview_image_source_url": "https://kitan.jp/products/tokidokisofubi/",
      "price_yen": 400,
      "variant_count": 5,
      "jan_code": null,
      "official_url": "https://kitan.jp/products/tokidokisofubi/",
      "source_url": "https://kitan.jp/products/tokidokisofubi/",
      "first_detected_at": "2026-05-14T09:13:25+09:00",
      "last_checked_at": "2026-05-14T09:13:25+09:00",
      "product_path": "products/kitanclub-tokidokisofubi.json"
    },
    {
      "id": "kitanclub-korokorozenmai-funkorogashi",
      "manufacturer_id": "kitanclub",
      "manufacturer_name": "キタンクラブ",
      "brand_name": null,
      "series_name": null,
      "product_name": "ころころゼンマイ フンコロガシ",
      "release_year": 2021,
      "release_month": 11,
      "release_week": null,
      "release_date": null,
      "preview_image_url": "https://kitan.jp/wp-content/uploads/2023/01/funkorogashiDP_800.jpg",
      "preview_image_source_url": "https://kitan.jp/products/korokorozenmai_funkorogashi/",
      "price_yen": 300,
      "variant_count": 5,
      "jan_code": null,
      "official_url": "https://kitan.jp/products/korokorozenmai_funkorogashi/",
      "source_url": "https://kitan.jp/products/korokorozenmai_funkorogashi/",
      "first_detected_at": "2026-05-14T09:13:25+09:00",
      "last_checked_at": "2026-05-14T09:13:25+09:00",
      "product_path": "products/kitanclub-korokorozenmai-funkorogashi.json"
    },
    {
      "id": "kitanclub-chiikawaecobag",
      "manufacturer_id": "kitanclub",
      "manufacturer_name": "キタンクラブ",
      "brand_name": null,
      "series_name": null,
      "product_name": "ちいかわ エコバッグ",
      "release_year": 2021,
      "release_month": 11,
      "release_week": null,
      "release_date": null,
      "preview_image_url": "https://kitan.jp/wp-content/uploads/2021/11/chiikawa_ecobag_DP_800.jpg",
      "preview_image_source_url": "https://kitan.jp/products/chiikawaecobag/",
      "price_yen": 500,
      "variant_count": 5,
      "jan_code": null,
      "official_url": "https://kitan.jp/products/chiikawaecobag/",
      "source_url": "https://kitan.jp/products/chiikawaecobag/",
      "first_detected_at": "2026-05-14T09:13:25+09:00",
      "last_checked_at": "2026-05-14T09:13:25+09:00",
      "product_path": "products/kitanclub-chiikawaecobag.json"
    },
    {
      "id": "kitanclub-kumonekokumoneko",
      "manufacturer_id": "kitanclub",
      "manufacturer_name": "キタンクラブ",
      "brand_name": null,
      "series_name": null,
      "product_name": "クモネコ フィギュアマスコット",
      "release_year": 2021,
      "release_month": 11,
      "release_week": null,
      "release_date": null,
      "preview_image_url": "https://kitan.jp/wp-content/uploads/2023/01/kumoneko_DP.jpg",
      "preview_image_source_url": "https://kitan.jp/products/kumonekokumoneko/",
      "price_yen": 300,
      "variant_count": 6,
      "jan_code": null,
      "official_url": "https://kitan.jp/products/kumonekokumoneko/",
      "source_url": "https://kitan.jp/products/kumonekokumoneko/",
      "first_detected_at": "2026-05-14T09:13:25+09:00",
      "last_checked_at": "2026-05-14T09:13:25+09:00",
      "product_path": "products/kitanclub-kumonekokumoneko.json"
    },
    {
      "id": "kitanclub-jujutsu-magnet-clip",
      "manufacturer_id": "kitanclub",
      "manufacturer_name": "キタンクラブ",
      "brand_name": null,
      "series_name": null,
      "product_name": "呪術廻戦 アクリルマグネットクリップ",
      "release_year": 2021,
      "release_month": 11,
      "release_week": null,
      "release_date": null,
      "preview_image_url": "https://kitan.jp/wp-content/uploads/2021/11/930f40846a7e735a804d8f729dc184c0-1.jpg",
      "preview_image_source_url": "https://kitan.jp/products/jujutsu_magnet_clip/",
      "price_yen": 300,
      "variant_count": 10,
      "jan_code": null,
      "official_url": "https://kitan.jp/products/jujutsu_magnet_clip/",
      "source_url": "https://kitan.jp/products/jujutsu_magnet_clip/",
      "first_detected_at": "2026-05-14T09:13:25+09:00",
      "last_checked_at": "2026-05-14T09:13:25+09:00",
      "product_path": "products/kitanclub-jujutsu-magnet-clip.json"
    },
    {
      "id": "kitanclub-jujutsu-ecobag",
      "manufacturer_id": "kitanclub",
      "manufacturer_name": "キタンクラブ",
      "brand_name": null,
      "series_name": null,
      "product_name": "呪術廻戦 エコバッグコレクション",
      "release_year": 2021,
      "release_month": 11,
      "release_week": null,
      "release_date": null,
      "preview_image_url": "https://kitan.jp/wp-content/uploads/2021/11/jujutsu_ecobag_DP-1.jpg",
      "preview_image_source_url": "https://kitan.jp/products/jujutsu_ecobag/",
      "price_yen": 500,
      "variant_count": 5,
      "jan_code": null,
      "official_url": "https://kitan.jp/products/jujutsu_ecobag/",
      "source_url": "https://kitan.jp/products/jujutsu_ecobag/",
      "first_detected_at": "2026-05-14T09:13:25+09:00",
      "last_checked_at": "2026-05-14T09:13:25+09:00",
      "product_path": "products/kitanclub-jujutsu-ecobag.json"
    },
    {
      "id": "qualia-ojigineko-sf",
      "manufacturer_id": "qualia",
      "manufacturer_name": "Qualia",
      "brand_name": null,
      "series_name": null,
      "product_name": "お辞儀猫 スタンドフィギュア",
      "release_year": 2021,
      "release_month": 11,
      "release_week": null,
      "release_date": null,
      "preview_image_url": "https://qualia-45.jp/wp-content/uploads/ojigineko_s-500x320.jpg",
      "preview_image_source_url": "https://qualia-45.jp/distinations/ojigineko_sf/",
      "price_yen": 300,
      "variant_count": 6,
      "jan_code": null,
      "official_url": "https://qualia-45.jp/distinations/ojigineko_sf/",
      "source_url": "https://qualia-45.jp/distinations/ojigineko_sf/",
      "first_detected_at": "2026-05-13T19:05:49+09:00",
      "last_checked_at": "2026-05-13T22:42:41+09:00",
      "product_path": "products/qualia-ojigineko-sf.json"
    },
    {
      "id": "qualia-aichi",
      "manufacturer_id": "qualia",
      "manufacturer_name": "Qualia",
      "brand_name": null,
      "series_name": null,
      "product_name": "ご当地！！みやげシリーズ 愛知ぷっくりラバーマスコット",
      "release_year": 2021,
      "release_month": 11,
      "release_week": null,
      "release_date": null,
      "preview_image_url": "https://qualia-45.jp/wp-content/uploads/gotouchi_aichi_bn-500x320.jpg",
      "preview_image_source_url": "https://qualia-45.jp/distinations/aichi/",
      "price_yen": 300,
      "variant_count": 6,
      "jan_code": null,
      "official_url": "https://qualia-45.jp/distinations/aichi/",
      "source_url": "https://qualia-45.jp/distinations/aichi/",
      "first_detected_at": "2026-05-13T19:05:49+09:00",
      "last_checked_at": "2026-05-13T22:42:41+09:00",
      "product_path": "products/qualia-aichi.json"
    },
    {
      "id": "qualia-ztmt-tm",
      "manufacturer_id": "qualia",
      "manufacturer_name": "Qualia",
      "brand_name": null,
      "series_name": null,
      "product_name": "ぜつめつきぐしゅんっ。 つながるマスコット",
      "release_year": 2021,
      "release_month": 11,
      "release_week": null,
      "release_date": null,
      "preview_image_url": "https://qualia-45.jp/wp-content/uploads/zetsumetsu_k_s-500x320.jpg",
      "preview_image_source_url": "https://qualia-45.jp/distinations/ztmt_tm/",
      "price_yen": 300,
      "variant_count": 7,
      "jan_code": null,
      "official_url": "https://qualia-45.jp/distinations/ztmt_tm/",
      "source_url": "https://qualia-45.jp/distinations/ztmt_tm/",
      "first_detected_at": "2026-05-13T19:05:49+09:00",
      "last_checked_at": "2026-05-13T22:42:41+09:00",
      "product_path": "products/qualia-ztmt-tm.json"
    },
    {
      "id": "qualia-drbf2",
      "manufacturer_id": "qualia",
      "manufacturer_name": "Qualia",
      "brand_name": null,
      "series_name": null,
      "product_name": "たべものに育てられた犬２ マスコットボールチェーン",
      "release_year": 2021,
      "release_month": 11,
      "release_week": null,
      "release_date": null,
      "preview_image_url": "https://qualia-45.jp/wp-content/uploads/tabemono_inu2_s-500x320.jpg",
      "preview_image_source_url": "https://qualia-45.jp/distinations/drbf2/",
      "price_yen": 300,
      "variant_count": 5,
      "jan_code": null,
      "official_url": "https://qualia-45.jp/distinations/drbf2/",
      "source_url": "https://qualia-45.jp/distinations/drbf2/",
      "first_detected_at": "2026-05-13T19:05:49+09:00",
      "last_checked_at": "2026-05-13T22:42:41+09:00",
      "product_path": "products/qualia-drbf2.json"
    },
    {
      "id": "qualia-nekojidaigeki",
      "manufacturer_id": "qualia",
      "manufacturer_name": "Qualia",
      "brand_name": null,
      "series_name": null,
      "product_name": "ねこ時代劇 造形コレクション",
      "release_year": 2021,
      "release_month": 11,
      "release_week": null,
      "release_date": null,
      "preview_image_url": "https://qualia-45.jp/wp-content/uploads/nekojidai_s-500x320.jpg",
      "preview_image_source_url": "https://qualia-45.jp/distinations/nekojidaigeki/",
      "price_yen": 300,
      "variant_count": 5,
      "jan_code": null,
      "official_url": "https://qualia-45.jp/distinations/nekojidaigeki/",
      "source_url": "https://qualia-45.jp/distinations/nekojidaigeki/",
      "first_detected_at": "2026-05-13T19:05:49+09:00",
      "last_checked_at": "2026-05-13T22:42:41+09:00",
      "product_path": "products/qualia-nekojidaigeki.json"
    },
    {
      "id": "qualia-vegemaru-rm",
      "manufacturer_id": "qualia",
      "manufacturer_name": "Qualia",
      "brand_name": null,
      "series_name": null,
      "product_name": "べじまる ぷっくりラバーマスコット",
      "release_year": 2021,
      "release_month": 11,
      "release_week": null,
      "release_date": null,
      "preview_image_url": "https://qualia-45.jp/wp-content/uploads/beji_s-500x320.jpg",
      "preview_image_source_url": "https://qualia-45.jp/distinations/vegemaru_rm/",
      "price_yen": 300,
      "variant_count": 6,
      "jan_code": null,
      "official_url": "https://qualia-45.jp/distinations/vegemaru_rm/",
      "source_url": "https://qualia-45.jp/distinations/vegemaru_rm/",
      "first_detected_at": "2026-05-13T19:05:49+09:00",
      "last_checked_at": "2026-05-13T22:42:41+09:00",
      "product_path": "products/qualia-vegemaru-rm.json"
    },
    {
      "id": "qualia-ikiteru-pan-mf",
      "manufacturer_id": "qualia",
      "manufacturer_name": "Qualia",
      "brand_name": null,
      "series_name": null,
      "product_name": "生きてるパン マスコットフィギュア",
      "release_year": 2021,
      "release_month": 11,
      "release_week": null,
      "release_date": null,
      "preview_image_url": "https://qualia-45.jp/wp-content/uploads/ikiterupan_s-500x320.jpg",
      "preview_image_source_url": "https://qualia-45.jp/distinations/ikiteru_pan_mf/",
      "price_yen": 300,
      "variant_count": 6,
      "jan_code": null,
      "official_url": "https://qualia-45.jp/distinations/ikiteru_pan_mf/",
      "source_url": "https://qualia-45.jp/distinations/ikiteru_pan_mf/",
      "first_detected_at": "2026-05-13T19:05:49+09:00",
      "last_checked_at": "2026-05-13T22:42:41+09:00",
      "product_path": "products/qualia-ikiteru-pan-mf.json"
    },
    {
      "id": "qualia-beko-higashi-aratame",
      "manufacturer_id": "qualia",
      "manufacturer_name": "Qualia",
      "brand_name": null,
      "series_name": null,
      "product_name": "神獣ベコたち 東の神々編 改",
      "release_year": 2021,
      "release_month": 11,
      "release_week": null,
      "release_date": null,
      "preview_image_url": "https://qualia-45.jp/wp-content/uploads/beko2kai_s-500x320.jpg",
      "preview_image_source_url": "https://qualia-45.jp/distinations/beko_higashi_aratame/",
      "price_yen": 300,
      "variant_count": 6,
      "jan_code": null,
      "official_url": "https://qualia-45.jp/distinations/beko_higashi_aratame/",
      "source_url": "https://qualia-45.jp/distinations/beko_higashi_aratame/",
      "first_detected_at": "2026-05-13T19:05:49+09:00",
      "last_checked_at": "2026-05-13T22:42:41+09:00",
      "product_path": "products/qualia-beko-higashi-aratame.json"
    },
    {
      "id": "stand-stones-acckimetsu1",
      "manufacturer_id": "stand-stones",
      "manufacturer_name": "スタンド・ストーンズ",
      "brand_name": null,
      "series_name": null,
      "product_name": "imagination accessory series鬼滅の刃 リングコレクション 壱ノ型",
      "release_year": 2021,
      "release_month": 11,
      "release_week": null,
      "release_date": null,
      "preview_image_url": "https://stasto.co.jp/web/wp-content/uploads/2021/08/KimetsuRing01.jpg",
      "preview_image_source_url": "https://stasto.co.jp/products_ss/acckimetsu1/",
      "price_yen": 300,
      "variant_count": null,
      "jan_code": null,
      "official_url": "https://stasto.co.jp/products_ss/acckimetsu1/",
      "source_url": "https://stasto.co.jp/products_ss/acckimetsu1/",
      "first_detected_at": "2026-05-14T09:13:25+09:00",
      "last_checked_at": "2026-05-14T09:13:25+09:00",
      "product_path": "products/stand-stones-acckimetsu1.json"
    },
    {
      "id": "stand-stones-onemutanjujutsu3",
      "manufacturer_id": "stand-stones",
      "manufacturer_name": "スタンド・ストーンズ",
      "brand_name": null,
      "series_name": null,
      "product_name": "おねむたん 呪術廻戦 三回戦",
      "release_year": 2021,
      "release_month": 11,
      "release_week": null,
      "release_date": null,
      "preview_image_url": "https://stasto.co.jp/web/wp-content/uploads/2022/03/onemutanJujutsu3.jpg",
      "preview_image_source_url": "https://stasto.co.jp/products_ss/onemutanjujutsu3/",
      "price_yen": 300,
      "variant_count": null,
      "jan_code": null,
      "official_url": "https://stasto.co.jp/products_ss/onemutanjujutsu3/",
      "source_url": "https://stasto.co.jp/products_ss/onemutanjujutsu3/",
      "first_detected_at": "2026-05-14T09:13:25+09:00",
      "last_checked_at": "2026-05-14T09:13:25+09:00",
      "product_path": "products/stand-stones-onemutanjujutsu3.json"
    },
    {
      "id": "stand-stones-onemukimetsu5arth",
      "manufacturer_id": "stand-stones",
      "manufacturer_name": "スタンド・ストーンズ",
      "brand_name": null,
      "series_name": null,
      "product_name": "おねむたん 鬼滅の刃 伍ノ型 にどね アースカラーＶｅｒ．",
      "release_year": 2021,
      "release_month": 11,
      "release_week": null,
      "release_date": null,
      "preview_image_url": "https://stasto.co.jp/web/wp-content/uploads/2021/08/OnemuKimetsu05.jpg",
      "preview_image_source_url": "https://stasto.co.jp/products_ss/onemukimetsu5arth/",
      "price_yen": 300,
      "variant_count": null,
      "jan_code": null,
      "official_url": "https://stasto.co.jp/products_ss/onemukimetsu5arth/",
      "source_url": "https://stasto.co.jp/products_ss/onemukimetsu5arth/",
      "first_detected_at": "2026-05-14T09:13:25+09:00",
      "last_checked_at": "2026-05-14T09:13:25+09:00",
      "product_path": "products/stand-stones-onemukimetsu5arth.json"
    },
    {
      "id": "stand-stones-kokmiehigurashi",
      "manufacturer_id": "stand-stones",
      "manufacturer_name": "スタンド・ストーンズ",
      "brand_name": null,
      "series_name": null,
      "product_name": "ひぐらしのなく頃に 卒 ここみえアクリルフィギュア",
      "release_year": 2021,
      "release_month": 11,
      "release_week": null,
      "release_date": null,
      "preview_image_url": "https://stasto.co.jp/web/wp-content/uploads/2021/08/kokomieHigurashi.jpg",
      "preview_image_source_url": "https://stasto.co.jp/products_ss/kokmiehigurashi/",
      "price_yen": 300,
      "variant_count": null,
      "jan_code": null,
      "official_url": "https://stasto.co.jp/products_ss/kokmiehigurashi/",
      "source_url": "https://stasto.co.jp/products_ss/kokmiehigurashi/",
      "first_detected_at": "2026-05-14T09:13:25+09:00",
      "last_checked_at": "2026-05-14T09:13:25+09:00",
      "product_path": "products/stand-stones-kokmiehigurashi.json"
    },
    {
      "id": "stand-stones-dpicjujutsu2",
      "manufacturer_id": "stand-stones",
      "manufacturer_name": "スタンド・ストーンズ",
      "brand_name": null,
      "series_name": null,
      "product_name": "デコラPICアクリル 呪術廻戦 二廻戦",
      "release_year": 2021,
      "release_month": 11,
      "release_week": null,
      "release_date": null,
      "preview_image_url": "https://stasto.co.jp/web/wp-content/uploads/2021/08/DecopicJujutsu02.jpg",
      "preview_image_source_url": "https://stasto.co.jp/products_ss/dpicjujutsu2/",
      "price_yen": 300,
      "variant_count": null,
      "jan_code": null,
      "official_url": "https://stasto.co.jp/products_ss/dpicjujutsu2/",
      "source_url": "https://stasto.co.jp/products_ss/dpicjujutsu2/",
      "first_detected_at": "2026-05-14T09:13:25+09:00",
      "last_checked_at": "2026-05-14T09:13:25+09:00",
      "product_path": "products/stand-stones-dpicjujutsu2.json"
    },
    {
      "id": "stand-stones-mandore",
      "manufacturer_id": "stand-stones",
      "manufacturer_name": "スタンド・ストーンズ",
      "brand_name": null,
      "series_name": null,
      "product_name": "マンドレイクコレクション",
      "release_year": 2021,
      "release_month": 11,
      "release_week": null,
      "release_date": null,
      "preview_image_url": "https://stasto.co.jp/web/wp-content/uploads/2021/08/mandrake.jpg",
      "preview_image_source_url": "https://stasto.co.jp/products_ss/mandore/",
      "price_yen": 200,
      "variant_count": null,
      "jan_code": null,
      "official_url": "https://stasto.co.jp/products_ss/mandore/",
      "source_url": "https://stasto.co.jp/products_ss/mandore/",
      "first_detected_at": "2026-05-14T09:13:25+09:00",
      "last_checked_at": "2026-05-14T09:13:25+09:00",
      "product_path": "products/stand-stones-mandore.json"
    },
    {
      "id": "toyscabin-20210727-366",
      "manufacturer_id": "toyscabin",
      "manufacturer_name": "トイズキャビン",
      "brand_name": null,
      "series_name": null,
      "product_name": "1/64横断歩道橋",
      "release_year": 2021,
      "release_month": 11,
      "release_week": null,
      "release_date": null,
      "preview_image_url": "https://toyscabin.com/product/upfiles/2021/07/%E6%AD%A9%E9%81%93%E6%A9%8B%E3%82%B3%E3%83%AC%E3%82%AF%E3%82%B7%E3%83%A7%E3%83%B3%EF%BC%BFweb%E7%94%A8%E3%83%81%E3%83%A9%E3%82%B7-thumb-980xauto-108.jpg",
      "preview_image_source_url": "https://toyscabin.com/product/20210727_366.php",
      "price_yen": 300,
      "variant_count": null,
      "jan_code": null,
      "official_url": "https://toyscabin.com/product/20210727_366.php",
      "source_url": "https://toyscabin.com/product/20210727_366.php",
      "first_detected_at": "2026-05-13T19:05:49+09:00",
      "last_checked_at": "2026-05-13T19:05:49+09:00",
      "product_path": "products/toyscabin-20210727-366.json"
    },
    {
      "id": "toyscabin-20210727-368",
      "manufacturer_id": "toyscabin",
      "manufacturer_name": "トイズキャビン",
      "brand_name": null,
      "series_name": null,
      "product_name": "【再々販】卓上呼び出しボタンコレクション",
      "release_year": 2021,
      "release_month": 11,
      "release_week": null,
      "release_date": null,
      "preview_image_url": "https://toyscabin.com/product/upfiles/2021/07/%E5%8D%93%E4%B8%8A%E5%91%BC%E3%81%B3%E5%87%BA%E3%81%97%E3%83%9C%E3%82%BF%E3%83%B3%EF%BC%BF%E5%86%8D%E8%B2%A9%EF%BC%BFWEB%E7%94%A8%E3%83%81%E3%83%A9%E3%82%B7-thumb-980xauto-110.jpg",
      "preview_image_source_url": "https://toyscabin.com/product/20210727_368.php",
      "price_yen": 300,
      "variant_count": null,
      "jan_code": null,
      "official_url": "https://toyscabin.com/product/20210727_368.php",
      "source_url": "https://toyscabin.com/product/20210727_368.php",
      "first_detected_at": "2026-05-13T19:05:49+09:00",
      "last_checked_at": "2026-05-13T19:05:49+09:00",
      "product_path": "products/toyscabin-20210727-368.json"
    },
    {
      "id": "toyscabin-20210727-367",
      "manufacturer_id": "toyscabin",
      "manufacturer_name": "トイズキャビン",
      "brand_name": null,
      "series_name": null,
      "product_name": "スチームパンク・モノクル",
      "release_year": 2021,
      "release_month": 11,
      "release_week": null,
      "release_date": null,
      "preview_image_url": "https://toyscabin.com/product/upfiles/2021/07/%E3%82%B9%E3%83%81%E3%83%BC%E3%83%A0%E3%83%91%E3%83%B3%E3%82%AFweb-thumb-980xauto-109.jpg",
      "preview_image_source_url": "https://toyscabin.com/product/20210727_367.php",
      "price_yen": 500,
      "variant_count": null,
      "jan_code": null,
      "official_url": "https://toyscabin.com/product/20210727_367.php",
      "source_url": "https://toyscabin.com/product/20210727_367.php",
      "first_detected_at": "2026-05-13T19:05:49+09:00",
      "last_checked_at": "2026-05-13T19:05:49+09:00",
      "product_path": "products/toyscabin-20210727-367.json"
    }
  ]
}
